exciton_tools/__init__.py
exciton_tools/elasticsearch/__init__.py
exciton_tools/elasticsearch/service.py
exciton_tools/minio/__init__.py
exciton_tools/minio/service.py
exciton_tools/prefect/__init__.py
exciton_tools/prefect/work_flag.py
exciton_tools/rabbitmq/__init__.py
exciton_tools/rabbitmq/service.py
exciton_tools/redis/__init__.py
exciton_tools/redis/work_flag.py
exciton_tools-0.5.1.dist-info/LICENSE
exciton_tools-0.5.1.dist-info/METADATA
exciton_tools-0.5.1.dist-info/WHEEL
exciton_tools-0.5.1.dist-info/top_level.txt
exciton_tools-0.5.1.dist-info/RECORD
